reportlab/__init__.py
reportlab/rl_config.py
reportlab/rl_settings.py
reportlab/fonts/00readme.txt
reportlab/fonts/DarkGarden-changelog.txt
reportlab/fonts/DarkGarden-copying-gpl.txt
reportlab/fonts/DarkGarden-copying.txt
reportlab/fonts/DarkGarden-readme.txt
reportlab/fonts/DarkGarden.sfd
reportlab/fonts/DarkGardenMK.afm
reportlab/fonts/DarkGardenMK.pfb
reportlab/fonts/PingFang.ttc
reportlab/fonts/PingFang_SC.ttf
reportlab/fonts/Vera.ttf
reportlab/fonts/VeraBI.ttf
reportlab/fonts/VeraBd.ttf
reportlab/fonts/VeraIt.ttf
reportlab/fonts/_a______.pfb
reportlab/fonts/_ab_____.pfb
reportlab/fonts/_abi____.pfb
reportlab/fonts/_ai_____.pfb
reportlab/fonts/_eb_____.pfb
reportlab/fonts/_ebi____.pfb
reportlab/fonts/_ei_____.pfb
reportlab/fonts/_er_____.pfb
reportlab/fonts/bitstream-vera-license.txt
reportlab/fonts/callig15.afm
reportlab/fonts/callig15.pfb
reportlab/fonts/cob_____.pfb
reportlab/fonts/cobo____.pfb
reportlab/fonts/com_____.pfb
reportlab/fonts/coo_____.pfb
reportlab/fonts/simsun.ttc
reportlab/fonts/sy______.pfb
reportlab/fonts/zd______.pfb
reportlab/fonts/zx______.pfb
reportlab/fonts/zy______.pfb
reportlab/graphics/__init__.py
reportlab/graphics/_renderPM.cpython-39-x86_64-linux-gnu.so
reportlab/graphics/renderPDF.py
reportlab/graphics/renderPM.py
reportlab/graphics/renderPS.py
reportlab/graphics/renderSVG.py
reportlab/graphics/renderbase.py
reportlab/graphics/shapes.py
reportlab/graphics/testdrawings.py
reportlab/graphics/testshapes.py
reportlab/graphics/transform.py
reportlab/graphics/utils.py
reportlab/graphics/widgetbase.py
reportlab/graphics/barcode/__init__.py
reportlab/graphics/barcode/code128.py
reportlab/graphics/barcode/code39.py
reportlab/graphics/barcode/code93.py
reportlab/graphics/barcode/common.py
reportlab/graphics/barcode/dmtx.py
reportlab/graphics/barcode/eanbc.py
reportlab/graphics/barcode/ecc200datamatrix.py
reportlab/graphics/barcode/fourstate.py
reportlab/graphics/barcode/lto.py
reportlab/graphics/barcode/qr.py
reportlab_eh-3.6.11.dist-info/LICENSE.txt
reportlab_eh-3.6.11.dist-info/METADATA
reportlab_eh-3.6.11.dist-info/WHEEL
reportlab_eh-3.6.11.dist-info/top_level.txt
reportlab_eh-3.6.11.dist-info/RECORD
